README
setup.py
etcpy/__init__.py
etcpy/__main__.py
etcpy/errors.py
etcpy.egg-info/PKG-INFO
etcpy.egg-info/SOURCES.txt
etcpy.egg-info/dependency_links.txt
etcpy.egg-info/not-zip-safe
etcpy.egg-info/requires.txt
etcpy.egg-info/top_level.txt