Metadata-Version: 1.1
Name: etcpy
Version: 0.1
Summary: etcd interface library
Home-page: http://code.pocketnix.org/etcpy/file/tip
Author: Da_Blitz
Author-email: code@pocketnix.org
License: MIT BSD
Download-URL: http://code.pocketnix.org/etcpy/archive/tip.tar.bz2
Keywords: etcd coreos cloud zookeeper
Platform: UNKNOWN
